context_helper/__init__.py
context_helper/context.py
context_helper-1.0.1.dist-info/LICENSE
context_helper-1.0.1.dist-info/METADATA
context_helper-1.0.1.dist-info/WHEEL
context_helper-1.0.1.dist-info/top_level.txt
context_helper-1.0.1.dist-info/RECORD
