Metadata-Version: 2.1
Name: context-helper
Version: 1.0.1
Summary: Context helpers for Python.
Home-page: https://gitlab.com/gloopio/context-helper
Author: Robert Parker
Author-email: rob@parob.com
License: MIT
Download-URL: https://gitlab.com/gloopio/context-helper/-/archive/v1.0.1/context-helper-v1.0.1.tar.gz
Keywords: Context,Helper
Platform: UNKNOWN
Classifier: Development Status :: 5 - Production/Stable
Classifier: Intended Audience :: Developers
Classifier: Programming Language :: Python :: 3
Classifier: License :: OSI Approved :: MIT License
Classifier: Operating System :: OS Independent
Requires-Dist: werkzeug (>=0.13)
